grasp2alm/__init__.py
grasp2alm/beam2alm.py
grasp2alm/beam_cut.py
grasp2alm/beam_gauss.py
grasp2alm/beam_grid.py
grasp2alm/beam_map.py
grasp2alm/beam_polar.py
grasp2alm/version.py
grasp2alm-0.1.2.dist-info/LICENSE
grasp2alm-0.1.2.dist-info/METADATA
grasp2alm-0.1.2.dist-info/WHEEL
grasp2alm-0.1.2.dist-info/RECORD
